makejinja/__init__.py
makejinja/__main__.py
makejinja/app.py
makejinja/cli.py
makejinja/config.py
makejinja/plugin.py
makejinja/py.typed
makejinja-2.8.2.dist-info/WHEEL
makejinja-2.8.2.dist-info/entry_points.txt
makejinja-2.8.2.dist-info/METADATA
makejinja-2.8.2.dist-info/RECORD
