Metadata-Version: 2.3
Name: makejinja
Version: 2.8.2
Summary: Generate entire directory structures using Jinja templates with support for external data and custom plugins
Keywords: jinja2,home-assistant,hassio,dashboard,lovelace,template,generator,cli,tool,library
Author: Mirko Lenz
Author-email: Mirko Lenz <mirko@mirkolenz.com>
Classifier: Development Status :: 5 - Production/Stable
Classifier: Environment :: Console
Classifier: Framework :: Pytest
Classifier: Intended Audience :: Developers
Classifier: Intended Audience :: End Users/Desktop
Classifier: Intended Audience :: System Administrators
Classifier: License :: OSI Approved :: MIT License
Classifier: Natural Language :: English
Classifier: Operating System :: OS Independent
Classifier: Programming Language :: Python :: 3.12
Classifier: Programming Language :: Python :: 3.13
Classifier: Programming Language :: Python :: 3.14
Classifier: Programming Language :: Python :: 3
Classifier: Topic :: File Formats
Classifier: Topic :: Home Automation
Classifier: Topic :: Software Development :: Code Generators
Classifier: Topic :: Software Development :: Libraries :: Python Modules
Classifier: Topic :: System :: Software Distribution
Classifier: Topic :: System :: Systems Administration
Classifier: Topic :: Text Processing :: Markup
Classifier: Topic :: Utilities
Classifier: Typing :: Typed
Requires-Dist: frozendict>=2,<3
Requires-Dist: jinja2>=3,<4
Requires-Dist: pyyaml>=6,<7
Requires-Dist: rich-click>=1,<2
Requires-Dist: typed-settings[attrs,cattrs,click]>=23,<26
Requires-Python: >=3.12, <4
Project-URL: Changelog, https://github.com/mirkolenz/makejinja/releases
Project-URL: Documentation, https://mirkolenz.github.io/makejinja/makejinja/cli.html
Project-URL: Homepage, https://mirkolenz.github.io/makejinja/
Project-URL: Issues, https://github.com/mirkolenz/makejinja/issues
Project-URL: Repository, https://github.com/mirkolenz/makejinja
